sb3/SbSessionEx.py
sb3/__init__.py
sb3/auth.py
sb3/client.py
sb3/querys.py
sciencebasepy/SbSession.py
sciencebasepy/__init__.py
sciencebasepy-2.0.20.dist-info/licenses/LICENSE.md
tests/__init__.py
tests/test_auth.py
tests/test_sbsessionex.py
sciencebasepy-2.0.20.dist-info/METADATA
sciencebasepy-2.0.20.dist-info/WHEEL
sciencebasepy-2.0.20.dist-info/top_level.txt
sciencebasepy-2.0.20.dist-info/RECORD
